RsCmwGsmMeas/RsCmwGsmMeas.py
RsCmwGsmMeas/__init__.py
RsCmwGsmMeas/enums.py
RsCmwGsmMeas/repcap.py
RsCmwGsmMeas/CustomFiles/__init__.py
RsCmwGsmMeas/CustomFiles/events.py
RsCmwGsmMeas/CustomFiles/reliability.py
RsCmwGsmMeas/CustomFiles/utilities.py
RsCmwGsmMeas/Implementations/Configure.py
RsCmwGsmMeas/Implementations/MultiEval.py
RsCmwGsmMeas/Implementations/Route.py
RsCmwGsmMeas/Implementations/Trigger.py
RsCmwGsmMeas/Implementations/__init__.py
RsCmwGsmMeas/Implementations/Configure_/MultiEval.py
RsCmwGsmMeas/Implementations/Configure_/RfSettings.py
RsCmwGsmMeas/Implementations/Configure_/__init__.py
RsCmwGsmMeas/Implementations/Configure_/MultiEval_/Ber.py
RsCmwGsmMeas/Implementations/Configure_/MultiEval_/FilterPy.py
RsCmwGsmMeas/Implementations/Configure_/MultiEval_/Limit.py
RsCmwGsmMeas/Implementations/Configure_/MultiEval_/ListPy.py
RsCmwGsmMeas/Implementations/Configure_/MultiEval_/Modulation.py
RsCmwGsmMeas/Implementations/Configure_/MultiEval_/Result.py
RsCmwGsmMeas/Implementations/Configure_/MultiEval_/Rotation.py
RsCmwGsmMeas/Implementations/Configure_/MultiEval_/Scount.py
RsCmwGsmMeas/Implementations/Configure_/MultiEval_/Smodulation.py
RsCmwGsmMeas/Implementations/Configure_/MultiEval_/Sswitching.py
RsCmwGsmMeas/Implementations/Configure_/MultiEval_/Vamos.py
RsCmwGsmMeas/Implementations/Configure_/MultiEval_/__init__.py
RsCmwGsmMeas/Implementations/Configure_/MultiEval_/Limit_/Epsk.py
RsCmwGsmMeas/Implementations/Configure_/MultiEval_/Limit_/Gmsk.py
RsCmwGsmMeas/Implementations/Configure_/MultiEval_/Limit_/PowerVsTime.py
RsCmwGsmMeas/Implementations/Configure_/MultiEval_/Limit_/Qam.py
RsCmwGsmMeas/Implementations/Configure_/MultiEval_/Limit_/__init__.py
RsCmwGsmMeas/Implementations/Configure_/MultiEval_/Limit_/Epsk_/PowerVsTime.py
RsCmwGsmMeas/Implementations/Configure_/MultiEval_/Limit_/Epsk_/Smodulation.py
RsCmwGsmMeas/Implementations/Configure_/MultiEval_/Limit_/Epsk_/Sswitching.py
RsCmwGsmMeas-3.7.30.5.dist-info/METADATA
RsCmwGsmMeas-3.7.30.5.dist-info/WHEEL
RsCmwGsmMeas-3.7.30.5.dist-info/top_level.txt
RsCmwGsmMeas-3.7.30.5.dist-info/RECORD
